_wrapper.cpython-39-darwin.so
pnot/__init__.py
pnot/py_solver.py
pnot/solver.py
pnot/utils.py
pnot-1.0.0.dist-info/licenses/LICENSE
pnot-1.0.0.dist-info/METADATA
pnot-1.0.0.dist-info/WHEEL
pnot-1.0.0.dist-info/top_level.txt
pnot-1.0.0.dist-info/RECORD
