Metadata-Version: 2.4
Name: pnot
Version: 1.0.0
Summary: Python package for nested optimal transport
Author-email: Songyan Hou <justinhou95@gmail.com>, Ruben Bontorno <rubensebastiano@gmail.com>
License-Expression: MIT
Project-URL: Homepage, https://github.com/justinhou95/NestedOT
Classifier: Programming Language :: Python :: 3
Classifier: Operating System :: OS Independent
Requires-Python: >=3.7
License-File: LICENSE
Requires-Dist: numpy
Requires-Dist: tqdm
Requires-Dist: pot
Provides-Extra: test
Requires-Dist: pytest; extra == "test"
Dynamic: license-file
Dynamic: requires-python
